sddp_discovery_protocol/__init__.py
sddp_discovery_protocol/__main__.py
sddp_discovery_protocol/client.py
sddp_discovery_protocol/constants.py
sddp_discovery_protocol/exceptions.py
sddp_discovery_protocol/internal_types.py
sddp_discovery_protocol/pkg_logging.py
sddp_discovery_protocol/py.typed
sddp_discovery_protocol/sddp_datagram.py
sddp_discovery_protocol/sddp_socket.py
sddp_discovery_protocol/server.py
sddp_discovery_protocol/util.py
sddp_discovery_protocol/version.py
sddp_discovery_protocol-1.5.0.dist-info/LICENSE
sddp_discovery_protocol-1.5.0.dist-info/METADATA
sddp_discovery_protocol-1.5.0.dist-info/WHEEL
sddp_discovery_protocol-1.5.0.dist-info/entry_points.txt
sddp_discovery_protocol-1.5.0.dist-info/RECORD
