Metadata-Version: 2.1
Name: sddp-discovery-protocol
Version: 1.5.0
Summary: Implementation of Control4's Simple Device Discovery Protocol (SDDP)
Home-page: https://github.com/sammck/sddp-discovery-protocol
License: MIT
Keywords: Control4,SDDP,SSDP,UPnP,protocol,multicast,UDP,discovery,network,automation,smart-home
Author: Sam McKelvie
Author-email: dev@mckelvie.org
Requires-Python: >=3.8,<4.0
Classifier: License :: OSI Approved :: MIT License
Classifier: Programming Language :: Python :: 3
Classifier: Programming Language :: Python :: 3.8
Classifier: Programming Language :: Python :: 3.9
Classifier: Programming Language :: Python :: 3.10
Classifier: Programming Language :: Python :: 3.11
Requires-Dist: netifaces-plus (>=0.12.0,<0.13.0)
Requires-Dist: requests (>=2.31.0,<3.0.0)
Requires-Dist: typing-extensions (>=4.7.1,<5.0.0)
Project-URL: Repository, https://github.com/sammck/sddp-discovery-protocol.git
